aepsych/__init__.py
aepsych/config.py
aepsych/config.pyi
aepsych/extensions.py
aepsych/plotting.py
aepsych/utils.py
aepsych/utils_logging.py
aepsych/version.py
aepsych/acquisition/__init__.py
aepsych/acquisition/bvn.py
aepsych/acquisition/lookahead.py
aepsych/acquisition/lookahead_utils.py
aepsych/acquisition/lse.py
aepsych/acquisition/mc_posterior_variance.py
aepsych/acquisition/mutual_information.py
aepsych/acquisition/objective/__init__.py
aepsych/acquisition/objective/multi_outcome.py
aepsych/acquisition/objective/objective.py
aepsych/acquisition/objective/semi_p.py
aepsych/benchmark/__init__.py
aepsych/benchmark/benchmark.py
aepsych/benchmark/example_problems.py
aepsych/benchmark/pathos_benchmark.py
aepsych/benchmark/problem.py
aepsych/benchmark/test_functions.py
aepsych/database/__init__.py
aepsych/database/data_fetcher.py
aepsych/database/db.py
aepsych/database/tables.py
aepsych/database/utils.py
aepsych/factory/__init__.py
aepsych/factory/default.py
aepsych/factory/ordinal.py
aepsych/factory/pairwise.py
aepsych/factory/song.py
aepsych/factory/utils.py
aepsych/generators/__init__.py
aepsych/generators/acqf_grid_search_generator.py
aepsych/generators/acqf_thompson_sampler_generator.py
aepsych/generators/base.py
aepsych/generators/epsilon_greedy_generator.py
aepsych/generators/grid_eval_acqf_generator.py
aepsych/generators/independent_acqf_generator.py
aepsych/generators/manual_generator.py
aepsych/generators/optimize_acqf_generator.py
aepsych/generators/random_generator.py
aepsych/generators/semi_p.py
aepsych/generators/sobol_generator.py
aepsych/kernels/__init__.py
aepsych/kernels/pairwisekernel.py
aepsych/likelihoods/__init__.py
aepsych/likelihoods/bernoulli.py
aepsych/likelihoods/mixed.py
aepsych/likelihoods/ordinal.py
aepsych/likelihoods/semi_p.py
aepsych/models/__init__.py
aepsych/models/base.py
aepsych/models/gp_classification.py
aepsych/models/gp_regression.py
aepsych/models/independent_gps.py
aepsych/models/monotonic_projection_gp.py
aepsych-0.8.0.dist-info/licenses/LICENSE
aepsych-0.8.0.dist-info/METADATA
aepsych-0.8.0.dist-info/WHEEL
aepsych-0.8.0.dist-info/entry_points.txt
aepsych-0.8.0.dist-info/top_level.txt
aepsych-0.8.0.dist-info/RECORD
