Metadata-Version: 2.4
Name: aepsych
Version: 0.8.0
Summary: Adaptive experimetation for psychophysics
Requires-Python: >=3.10
License-File: LICENSE
Requires-Dist: numpy<2.0,>=1.20
Requires-Dist: matplotlib
Requires-Dist: torch
Requires-Dist: scipy==1.14.1
Requires-Dist: SQLAlchemy==1.4.46
Requires-Dist: dill
Requires-Dist: pandas
Requires-Dist: aepsych_client
Requires-Dist: statsmodels
Requires-Dist: botorch==0.12.0
Provides-Extra: dev
Requires-Dist: tqdm; extra == "dev"
Requires-Dist: pathos; extra == "dev"
Requires-Dist: multiprocess; extra == "dev"
Requires-Dist: torcheval; extra == "dev"
Requires-Dist: coverage; extra == "dev"
Requires-Dist: ruff; extra == "dev"
Requires-Dist: sqlalchemy-stubs; extra == "dev"
Requires-Dist: mypy==1.14.0; extra == "dev"
Requires-Dist: parameterized; extra == "dev"
Requires-Dist: scikit-learn; extra == "dev"
Requires-Dist: black==24.4.2; extra == "dev"
Requires-Dist: ruff-api==0.1.0; extra == "dev"
Requires-Dist: stdlibs==2024.1.28; extra == "dev"
Requires-Dist: ufmt==2.8.0; extra == "dev"
Requires-Dist: usort==1.0.8.post1; extra == "dev"
Provides-Extra: benchmark
Requires-Dist: tqdm; extra == "benchmark"
Requires-Dist: pathos; extra == "benchmark"
Requires-Dist: multiprocess; extra == "benchmark"
Requires-Dist: torcheval; extra == "benchmark"
Dynamic: description
Dynamic: description-content-type
Dynamic: license-file
Dynamic: provides-extra
Dynamic: requires-dist
Dynamic: requires-python
Dynamic: summary
